experiment/__init__.py
experiment/corpus.py
experiment/report.py
ncgocr/__init__.py
ncgocr/concept.py
ncgocr/corpus_craft.py
ncgocr/extractor.py
ncgocr/gopattern.py
ncgocr/learning.py
ncgocr/ncgocr.py
ncgocr/pattern_regex.py
ncgocr-1.0.2.data/data/input/11532192.txt
ncgocr-1.0.2.data/data/input/11597317.txt
ncgocr-1.0.2.data/data/input/11897010.txt
ncgocr-1.0.2.data/data/input/12079497.txt
ncgocr-1.0.2.data/data/input/12546709.txt
ncgocr-1.0.2.data/data/input/12585968.txt
ncgocr-1.0.2.dist-info/DESCRIPTION.rst
ncgocr-1.0.2.dist-info/METADATA
ncgocr-1.0.2.dist-info/RECORD
ncgocr-1.0.2.dist-info/WHEEL
ncgocr-1.0.2.dist-info/metadata.json
ncgocr-1.0.2.dist-info/top_level.txt
