Metadata-Version: 2.0
Name: ncgocr
Version: 1.0.2
Summary: Named Concept Gene Ontology Concept Recognition
Home-page: https://github.com/jeroyang/ncgocr
Author: Chia-Jung, Yang
Author-email: jeroyang@gmail.com
License: MIT
Keywords: ncgocr
Platform: UNKNOWN
Classifier: Development Status :: 4 - Beta
Classifier: Intended Audience :: Developers
Classifier: License :: OSI Approved :: MIT License
Classifier: Natural Language :: English
Classifier: Programming Language :: Python :: 3
Classifier: Programming Language :: Python :: 3.5
Classifier: Programming Language :: Python :: 3.6
Requires-Dist: progressbar2 (==3.12.0)
Requires-Dist: acora (==2.0)
Requires-Dist: lxml (==3.7.3)
Requires-Dist: intervaltree (==2.1.0)
Requires-Dist: mock (==2.0.0)
Requires-Dist: scikit-learn (==0.18.1)
Requires-Dist: numpy (==1.12.0)
Requires-Dist: scipy (==0.18.1)
Requires-Dist: txttk (==0.10.0)
